_libvmi.abi3.so
libvmi/slat_cdef.h
libvmi/libvmi.py
libvmi/__init__.py
libvmi/libvmi_cdef.h
libvmi/glib_cdef.h
libvmi/event.py
libvmi/libvmi_extra_cdef.h
libvmi/libvmi_build.py
libvmi/events_cdef.h
libvmi.libs/libvmi-fcaa3834.so.0.0.15
libvmi.libs/libjson-c-53e1d64f.so.4.0.0
libvmi-3.7.1.dist-info/top_level.txt
libvmi-3.7.1.dist-info/RECORD
libvmi-3.7.1.dist-info/LICENSE
libvmi-3.7.1.dist-info/METADATA
libvmi-3.7.1.dist-info/WHEEL
