Metadata-Version: 2.1
Name: libvmi
Version: 3.7.1
Summary: Python interface to LibVMI
Home-page: https://github.com/libvmi/python
Author: Mathieu Tarral
Author-email: mathieu.tarral@protonmail.com
License-File: LICENSE
Requires-Dist: cffi>=1.6.0
Requires-Dist: future
Requires-Dist: enum34; python_version < "3.4"
